zep_cloud/__init__.py
zep_cloud/base_client.py
zep_cloud/client.py
zep_cloud/context/__init__.py
zep_cloud/context/client.py
zep_cloud/context/raw_client.py
zep_cloud/core/__init__.py
zep_cloud/core/api_error.py
zep_cloud/core/client_wrapper.py
zep_cloud/core/datetime_utils.py
zep_cloud/core/file.py
zep_cloud/core/force_multipart.py
zep_cloud/core/http_client.py
zep_cloud/core/http_response.py
zep_cloud/core/jsonable_encoder.py
zep_cloud/core/pydantic_utilities.py
zep_cloud/core/query_encoder.py
zep_cloud/core/remove_none_from_dict.py
zep_cloud/core/request_options.py
zep_cloud/core/serialization.py
zep_cloud/environment.py
zep_cloud/errors/__init__.py
zep_cloud/errors/bad_request_error.py
zep_cloud/errors/internal_server_error.py
zep_cloud/errors/not_found_error.py
zep_cloud/external_clients/graph.py
zep_cloud/external_clients/ontology.py
zep_cloud/external_clients/user.py
zep_cloud/graph/__init__.py
zep_cloud/graph/client.py
zep_cloud/graph/edge/__init__.py
zep_cloud/graph/edge/client.py
zep_cloud/graph/edge/raw_client.py
zep_cloud/graph/episode/__init__.py
zep_cloud/graph/episode/client.py
zep_cloud/graph/episode/raw_client.py
zep_cloud/graph/node/__init__.py
zep_cloud/graph/node/client.py
zep_cloud/graph/node/raw_client.py
zep_cloud/graph/raw_client.py
zep_cloud/graph/utils.py
zep_cloud/project/__init__.py
zep_cloud/project/client.py
zep_cloud/project/raw_client.py
zep_cloud/py.typed
zep_cloud/task/__init__.py
zep_cloud/task/client.py
zep_cloud/task/raw_client.py
zep_cloud/thread/__init__.py
zep_cloud/thread/client.py
zep_cloud/thread/message/__init__.py
zep_cloud/thread/message/client.py
zep_cloud/thread/message/raw_client.py
zep_cloud/thread/raw_client.py
zep_cloud/thread/types/__init__.py
zep_cloud/thread/types/thread_get_user_context_request_mode.py
zep_cloud/types/__init__.py
zep_cloud/types/add_thread_messages_request.py
zep_cloud/types/add_thread_messages_response.py
zep_cloud/types/add_triple_response.py
zep_cloud/types/api_error.py
zep_cloud-3.16.0.dist-info/LICENSE
zep_cloud-3.16.0.dist-info/METADATA
zep_cloud-3.16.0.dist-info/WHEEL
zep_cloud-3.16.0.dist-info/RECORD
